<?xml version="1.0" encoding="utf-8"?>
<metadata>
	<layout
			title="PLG_FAF_TS_DE_FORM_TITLE"
			option="PLG_FAF_TS_DE_FORM_OPTION"
			>
		<message>
			<![CDATA[PLG_FAF_TS_DE_FORM_DESC]]>
		</message>
	</layout>

	<group type="fields"
	       title="PLG_FIELDSANDFILTERS_FORM_GROUP_FIELDS_TITLE">
		<message>
			<![CDATA[PLG_FIELDSANDFILTERS_FORM_GROUP_FIELDS_DESC]]>
		</message>
	</group>

	<form>
		<!-- Add fields to the properties variables for the plugin type. -->
		<fields name="properties">
			<field
					name="mode"
					type="hidden"
					value="field.text"
					/>
		</fields>

		<!-- Add fields to the parameters object for the plugin type. -->
		<fields name="params">
			<fields name="type">
				<fieldset name="type">
					<field
							name="format"
							type="list"
							class="inputbox"
							default="DATE_FORMAT_LC"
							label="PLG_FAF_TS_DE_FORM_FORMAT_LBL"
							description="PLG_FAF_TS_DE_FORM_FORMAT_DESC"
							>
						<option value="l, d F Y">PLG_FAF_TS_DE_DATE_FORMAT_LDFY</option>
						<option value="l, d F Y H:i">PLG_FAF_TS_DE_DATE_FORMAT_LDFYHI</option>
						<option value="d F Y">PLG_FAF_TS_DE_DATE_FORMAT_DFY</option>
						<option value="Y-m-d">PLG_FAF_TS_DE_DATE_FORMAT_YMD</option>
						<option value="custom">PLG_FAF_TS_DE_OPTION_CUSTOM</option>
					</field>
					<field
							name="format_custom"
							type="input"
							class="inputbox"
							label="PLG_FAF_TS_DE_FORM_FORMAT_CUSTOM_LBL"
							description="PLG_FAF_TS_DE_FORM_FORMAT_CUSTOM_DESC"
							/>
					<field
							name="field_layout"
							type="fieldsandfiltersPluginLayout"
							layoutFolder="field"
							label="PLG_FAF_TS_DE_FORM_FIELD_LAYOUT_LBL"
							description="PLG_FAF_TS_DE_FORM_FIELD_LAYOUT_DESC"
							/>
				</fieldset>
			</fields>
		</fields>
	</form>
</metadata>