<?xml version="1.0" encoding="utf-8"?>
<extension type="library" version="2.5" method="upgrade">
	<name>Kextensions Library</name>
	<libraryname>kextensions</libraryname>
	<creationDate>2015-01-30</creationDate>
	<copyright>Copyright (C) 2012 KES - Kulka Tomasz . All rights reserved.</copyright>
	<license>GNU General Public License version 3 or later; see License.txt</license>
	<author>KES - Kulka Tomasz</author>
	<authorEmail>kes@kextensions.com</authorEmail>
	<authorUrl>http://www.kextensions.com</authorUrl>
	<version>1.3.1</version>
	<files>
		<filename>index.html</filename>
		<filename>License.txt</filename>
		<folder>array</folder>
		<folder>buffer</folder>
		<folder>controller</folder>
		<folder>file</folder>
		<folder>form</folder>
		<folder>joomla</folder>
		<folder>language</folder>
		<folder>log</folder>
		<folder>module</folder>
		<folder>plugin</folder>
		<folder>request</folder>
		<folder>user</folder>
		<folder>xml</folder>
	</files>
	<languages>
		<language tag="en-GB">en-GB.lib_kextensions.ini</language>
	</languages>
</extension>
